aios_sdk/__init__.py
aios_sdk/cli.py
aios_sdk/inference.py
aios_sdk/models.py
aios_sdk/rpc/app_state_pb2.py
aios_sdk/rpc/app_state_pb2.pyi
aios_sdk/rpc/app_state_pb2_grpc.py
aios_sdk/rpc/app_state_pb2_grpc.pyi
aios_sdk/rpc/helloworld_pb2.py
aios_sdk/rpc/helloworld_pb2.pyi
aios_sdk/rpc/helloworld_pb2_grpc.py
aios_sdk/rpc/helloworld_pb2_grpc.pyi
aios_sdk/rpc/inference_pb2.py
aios_sdk/rpc/inference_pb2.pyi
aios_sdk/rpc/inference_pb2_grpc.py
aios_sdk/rpc/inference_pb2_grpc.pyi
aios_sdk/rpc/kill_pb2.py
aios_sdk/rpc/kill_pb2.pyi
aios_sdk/rpc/kill_pb2_grpc.py
aios_sdk/rpc/kill_pb2_grpc.pyi
aios_sdk/rpc/models_pb2.py
aios_sdk/rpc/models_pb2.pyi
aios_sdk/rpc/models_pb2_grpc.py
aios_sdk/rpc/models_pb2_grpc.pyi
aios_sdk/rpc/system_info_pb2.py
aios_sdk/rpc/system_info_pb2.pyi
aios_sdk/rpc/system_info_pb2_grpc.py
aios_sdk/rpc/system_info_pb2_grpc.pyi
aios_sdk/rpc/websocket_pb2.py
aios_sdk/rpc/websocket_pb2.pyi
aios_sdk/rpc/websocket_pb2_grpc.py
aios_sdk/rpc/websocket_pb2_grpc.pyi
aios_sdk-0.1.10.dist-info/METADATA
aios_sdk-0.1.10.dist-info/WHEEL
aios_sdk-0.1.10.dist-info/entry_points.txt
aios_sdk-0.1.10.dist-info/RECORD
