Metadata-Version: 2.1
Name: aios-sdk
Version: 0.1.10
Summary: 
Author: Ginkoe
Author-email: ginkoe@protonmail.com
Requires-Python: >=3.12,<4.0
Classifier: Programming Language :: Python :: 3
Classifier: Programming Language :: Python :: 3.12
Requires-Dist: grpcio (>=1.62.1,<2.0.0)
Requires-Dist: protobuf (>=5.26.1,<6.0.0)
